README.rst
filesystem_tree.py
setup.py
filesystem_tree.egg-info/PKG-INFO
filesystem_tree.egg-info/SOURCES.txt
filesystem_tree.egg-info/dependency_links.txt
filesystem_tree.egg-info/top_level.txt